pmodoro/__init__.py
pmodoro/__main__.py
pmodoro/cli.py
pmodoro/config.py
pmodoro/pmdoro.py
pmodoro/progress.py
pmodoro-1.0.0.dist-info/licenses/LICENSE
test/__init__.py
test/test_pmodoro.py
pmodoro-1.0.0.dist-info/METADATA
pmodoro-1.0.0.dist-info/WHEEL
pmodoro-1.0.0.dist-info/top_level.txt
pmodoro-1.0.0.dist-info/RECORD
