Metadata-Version: 2.4
Name: pmodoro
Version: 1.0.0
Summary: A Pomodoro timer in CLI
Home-page: https://github.com/Zuiluj/cli-pomodoro-timer
Author: Juliuz Llanillo
Author-email: christianllanillo@gmail.com
Classifier: Programming Language :: Python :: 3
Classifier: License :: OSI Approved :: MIT License
Classifier: Operating System :: OS Independent
License-File: LICENSE
Requires-Dist: click==8.1.8
Requires-Dist: colorama==0.4.6
Requires-Dist: markdown-it-py==3.0.0
Requires-Dist: mdurl==0.1.2
Requires-Dist: mypy_extensions==1.1.0
Requires-Dist: packaging==25.0
Requires-Dist: pathspec==0.12.1
Requires-Dist: platformdirs==4.3.8
Requires-Dist: Pygments==2.19.1
Requires-Dist: rich==14.0.0
Requires-Dist: shellingham==1.5.4
Requires-Dist: typer==0.15.4
Requires-Dist: typing_extensions==4.13.2
Dynamic: author
Dynamic: author-email
Dynamic: classifier
Dynamic: description
Dynamic: description-content-type
Dynamic: home-page
Dynamic: license-file
Dynamic: requires-dist
Dynamic: summary
